README.md
setup.cfg
setup.py
discoset/__init__.py
discoset/__main__.py
discoset/config.py
discoset/tests.py
discoset/worker.py
discoset.egg-info/PKG-INFO
discoset.egg-info/SOURCES.txt
discoset.egg-info/dependency_links.txt
discoset.egg-info/entry_points.txt
discoset.egg-info/requires.txt
discoset.egg-info/top_level.txt