Metadata-Version: 2.1
Name: discoset
Version: 0.9.3
Summary: Small script to setup symlinks to dotfiles
Home-page: https://github.com/chsigi/discoset
Author: Christoph Echtinger-Sieghart
Author-email: s@hands-on-imperative.org
License: MIT
Keywords: dotfiles,symlink,configs
Platform: UNKNOWN
Classifier: Development Status :: 4 - Beta
Classifier: Intended Audience :: Developers
Classifier: Topic :: Software Development :: Build Tools
Classifier: License :: OSI Approved :: MIT License
Classifier: Programming Language :: Python :: 3
